[
  {
    "mid": 486989780,
    "name": "老麦的工具库",
    "sign": "前字节、百度，专注效率神器和AI技术，更新工具库里1000个神器（只此一号，其他",
    "fans": "bilibili 知名UP主"
  },
  {
    "mid": 3546884870244925,
    "name": "杰森的效率工坊",
    "sign": "邮箱: jasoneffidemo@hotmail.com\n资料下载: jaso",
    "fans": ""
  },
  {
    "mid": 281120100,
    "name": "我是阿众",
    "sign": "关注AI效率提升 & AI 工具推荐，合作：reborn0502",
    "fans": "bilibili 知名科技UP主"
  },
  {
    "mid": 315945401,
    "name": "Kiven大汉堡",
    "sign": "产品经理/个人生产力教练打造个人AI笔记系统，连接想法、行动、目标方法论通用，适",
    "fans": ""
  },
  {
    "mid": 325864133,
    "name": "飞天闪客",
    "sign": "专治不明白，合作：dibingfa2020",
    "fans": "bilibili 知名科普UP主"
  },
  {
    "mid": 16433002,
    "name": "隔壁的程序员老王",
    "sign": "喜欢分享知识的谷歌程序员  知识星球：https://t.zsxq.com/ub",
    "fans": "bilibili 知名科普UP主"
  },
  {
    "mid": 1815948385,
    "name": "马克的技术工作坊",
    "sign": "分享工具和方法、提升生产力",
    "fans": ""
  },
  {
    "mid": 1235535223,
    "name": "数字黑魔法",
    "sign": "聊聊AI最新动向，佛系开源。联系方式：blackmagican.com",
    "fans": ""
  },
  {
    "mid": 316183842,
    "name": "技术爬爬虾",
    "sign": "分享好玩实用的软件DIY，全网同名，商务合作: zaihengderen ",
    "fans": "bilibili 知名科技UP主"
  },
  {
    "mid": 71216218,
    "name": "浪里小白龙7",
    "sign": "合作/获取插件请加：v587xbailong",
    "fans": ""
  },
  {
    "mid": 332569278,
    "name": "Echo_NebulaPKM",
    "sign": "发一些PKM和TFT相关内容，可视化笔记（视觉思考）；https://www.n",
    "fans": ""
  }
]